sync_offset_tool/__init__.py
sync_offset_tool/sync_offset.py
sync_offset_tool-1.3.0.dist-info/licenses/LICENSE
sync_offset_tool-1.3.0.dist-info/METADATA
sync_offset_tool-1.3.0.dist-info/WHEEL
sync_offset_tool-1.3.0.dist-info/entry_points.txt
sync_offset_tool-1.3.0.dist-info/top_level.txt
sync_offset_tool-1.3.0.dist-info/RECORD
