Metadata-Version: 2.4
Name: sync-offset-tool
Version: 1.3.0
Summary: A command-line utility to measure audio sync offsets between MKV files
Home-page: https://github.com/gmipf/sync-offset-tool
Author: gmipf
License: MIT
Classifier: Programming Language :: Python :: 3
Classifier: License :: OSI Approved :: MIT License
Classifier: Operating System :: OS Independent
Requires-Python: >=3.8
License-File: LICENSE
Requires-Dist: numpy
Requires-Dist: scipy
Dynamic: license-file
